{
  "info": {
    "description": "Grape detection annotation for Syrah variety",
    "version": "1.0",
    "year": 2025,
    "contributor": "Embrapa WGISD Dataset",
    "source": "Field captured grape images",
    "license": {
      "name": "Creative Commons Attribution 4.0 International",
      "url": "https://creativecommons.org/licenses/by/4.0/"
    },
    "berry_count": 488
  },
  "images": [
    {
      "id": 9328754395,
      "width": 1920,
      "height": 1080,
      "file_name": "SYH_2017-04-27_1273.jpg",
      "size": 659777,
      "format": "JPG",
      "url": "",
      "hash": "",
      "status": "success",
      "variety": "Syrah",
      "berry_count": 488
    }
  ],
  "annotations": [
    {
      "id": 3219696395,
      "image_id": 9328754395,
      "category_id": 1,
      "bbox": [
        1562,
        600,
        192,
        311
      ],
      "area": 59712,
      "iscrowd": 0
    },
    {
      "id": 7406574395,
      "image_id": 9328754395,
      "category_id": 1,
      "bbox": [
        1321,
        471,
        179,
        264
      ],
      "area": 47256,
      "iscrowd": 0
    },
    {
      "id": 8001308395,
      "image_id": 9328754395,
      "category_id": 1,
      "bbox": [
        888,
        520,
        173,
        362
      ],
      "area": 62626,
      "iscrowd": 0
    },
    {
      "id": 6321173395,
      "image_id": 9328754395,
      "category_id": 1,
      "bbox": [
        746,
        561,
        170,
        126
      ],
      "area": 21420,
      "iscrowd": 0
    },
    {
      "id": 2355234395,
      "image_id": 9328754395,
      "category_id": 1,
      "bbox": [
        205,
        751,
        140,
        121
      ],
      "area": 16940,
      "iscrowd": 0
    },
    {
      "id": 6013110395,
      "image_id": 9328754395,
      "category_id": 1,
      "bbox": [
        517,
        551,
        226,
        323
      ],
      "area": 72998,
      "iscrowd": 0
    },
    {
      "id": 5177063395,
      "image_id": 9328754395,
      "category_id": 1,
      "bbox": [
        654,
        633,
        102,
        168
      ],
      "area": 17136,
      "iscrowd": 0
    },
    {
      "id": 3918494395,
      "image_id": 9328754395,
      "category_id": 1,
      "bbox": [
        1216,
        299,
        228,
        516
      ],
      "area": 117648,
      "iscrowd": 0
    },
    {
      "id": 6659257395,
      "image_id": 9328754395,
      "category_id": 1,
      "bbox": [
        232,
        18,
        96,
        261
      ],
      "area": 25056,
      "iscrowd": 0
    },
    {
      "id": 9559843395,
      "image_id": 9328754395,
      "category_id": 1,
      "bbox": [
        401,
        415,
        82,
        123
      ],
      "area": 10086,
      "iscrowd": 0
    }
  ],
  "categories": [
    {
      "id": 1,
      "name": "GRAPE_CLUSTER",
      "supercategory": "GRAPE"
    }
  ]
}